did_plc/__init__.py
did_plc_client/__init__.py
did_plc_server/__init__.py
did_plc-0.0.0.dist-info/LICENSE
did_plc-0.0.0.dist-info/METADATA
did_plc-0.0.0.dist-info/WHEEL
did_plc-0.0.0.dist-info/RECORD
